imout/__init__.py
imout-0.0.1.dist-info/LICENSE.txt
imout-0.0.1.dist-info/METADATA
imout-0.0.1.dist-info/WHEEL
imout-0.0.1.dist-info/top_level.txt
imout-0.0.1.dist-info/RECORD
