Metadata-Version: 2.1
Name: imout
Version: 0.0.1
Summary: To fetch the results after model development
Home-page: UNKNOWN
Author: Rahul Kumar
Author-email: rahulrkumar9000@gmail.com
License: UNKNOWN
Platform: UNKNOWN
Classifier: Programming Language :: Python :: 3
Classifier: License :: OSI Approved :: MIT License
Classifier: Operating System :: OS Independent
